MANIFEST.in
README
setup.cfg
setup.py
lingo/__init__.py
lingo/attachment.py
lingo/database.py
lingo/errors.py
lingo/lingo.py
lingo.egg-info/PKG-INFO
lingo.egg-info/SOURCES.txt
lingo.egg-info/dependency_links.txt
lingo.egg-info/not-zip-safe
lingo.egg-info/requires.txt
lingo.egg-info/top_level.txt