Metadata-Version: 1.1
Name: lingo
Version: 0.8.3
Summary: A simple MongoDB/CouchDB ORM for Python
Home-page: https://github.com/BasementCat/lingo
Author: BasementCat
Author-email: basementcat@basementcat.net
License: UNKNOWN
Keywords: mongo mongodb orm python couchdb
Platform: UNKNOWN
Classifier: Development Status :: 3 - Alpha
Classifier: Intended Audience :: Developers
Classifier: License :: Other/Proprietary License
Classifier: Natural Language :: English
Classifier: Operating System :: OS Independent
Classifier: Programming Language :: Python :: 2
Classifier: Topic :: Database
Classifier: Topic :: Software Development :: Libraries
